mcmsmp/__init__.py
mcmsmp/exceptions.py
mcmsmp/notifications.py
mcmsmp/objects.py
mcmsmp/py.typed
mcmsmp/trigger.py
mcmsmp-0.1.4.dist-info/licenses/LICENSE
mcmsmp-0.1.4.dist-info/METADATA
mcmsmp-0.1.4.dist-info/WHEEL
mcmsmp-0.1.4.dist-info/top_level.txt
mcmsmp-0.1.4.dist-info/RECORD
