Metadata-Version: 2.4
Name: mcmsmp
Version: 0.1.4
Summary: Python client for Minecraft Management Server Protocol
Author-email: dngynq <dngynq@gmail.com>
License: MIT
Project-URL: Homepage, https://github.com/DngYnQ/mcmsmp
Project-URL: Repository, https://github.com/DngYnQ/mcmsmp
Project-URL: Documentation, https://github.com/DngYnQ/mcmsmp#readme
Project-URL: Changelog, https://github.com/DngYnQ/mcmsmp/releases
Project-URL: Issues, https://github.com/DngYnQ/mcmsmp/issues
Keywords: minecraft,rpc,websocket,server-management,game-server
Classifier: Development Status :: 4 - Beta
Classifier: Intended Audience :: Developers
Classifier: Topic :: Software Development :: Libraries :: Python Modules
Classifier: Topic :: Games/Entertainment
Classifier: License :: OSI Approved :: MIT License
Classifier: Programming Language :: Python :: 3
Classifier: Programming Language :: Python :: 3.8
Classifier: Programming Language :: Python :: 3.9
Classifier: Programming Language :: Python :: 3.10
Classifier: Programming Language :: Python :: 3.11
Classifier: Programming Language :: Python :: 3.12
Classifier: Programming Language :: Python :: 3.13
Classifier: Operating System :: OS Independent
Requires-Python: >=3.8
License-File: LICENSE
Requires-Dist: websockets>=15.0.1
Requires-Dist: jsonrpcclient>=4.0.3
Provides-Extra: dev
Requires-Dist: pytest>=7.0.0; extra == "dev"
Requires-Dist: pytest-asyncio>=0.21.0; extra == "dev"
Requires-Dist: black>=23.0.0; extra == "dev"
Requires-Dist: mypy>=1.0.0; extra == "dev"
Requires-Dist: flake8>=6.0.0; extra == "dev"
Provides-Extra: docs
Requires-Dist: sphinx>=7.0.0; extra == "docs"
Requires-Dist: sphinx-rtd-theme>=1.0.0; extra == "docs"
Dynamic: license-file
